<annotation>
	<folder>Copenhagen_66</folder>
	<filename>Copenhagen_66_3.jpeg</filename>
	<path>/home/yoeri/Work/OMR/data/Train/object_detection_data/non-public/annotated_source_images/revised_ground_truth/Non_IDEM/Copenhagen_Chansonnier/Copenhagen_66/Copenhagen_66_3.jpeg</path>
	<source>
		<database>Unknown</database>
	</source>
	<size>
		<width>1024</width>
		<height>1521</height>
		<depth>3</depth>
	</size>
	<segmented>0</segmented>
	<object>
		<name>c clef_5</name>
		<pose>Unspecified</pose>
		<truncated>0</truncated>
		<difficult>0</difficult>
		<bndbox>
			<xmin>281</xmin>
			<ymin>751</ymin>
			<xmax>299</xmax>
			<ymax>806</ymax>
		</bndbox>
	</object>
	<object>
		<name>flat_6</name>
		<pose>Unspecified</pose>
		<truncated>0</truncated>
		<difficult>0</difficult>
		<bndbox>
			<xmin>292</xmin>
			<ymin>718</ymin>
			<xmax>308</xmax>
			<ymax>792</ymax>
		</bndbox>
	</object>
	<object>
		<name>colored breve_4</name>
		<pose>Unspecified</pose>
		<truncated>0</truncated>
		<difficult>0</difficult>
		<bndbox>
			<xmin>308</xmin>
			<ymin>752</ymin>
			<xmax>331</xmax>
			<ymax>783</ymax>
		</bndbox>
	</object>
	<object>
		<name>semiminim_5</name>
		<pose>Unspecified</pose>
		<truncated>0</truncated>
		<difficult>0</difficult>
		<bndbox>
			<xmin>329</xmin>
			<ymin>711</ymin>
			<xmax>346</xmax>
			<ymax>804</ymax>
		</bndbox>
	</object>
	<object>
		<name>semiminim_6</name>
		<pose>Unspecified</pose>
		<truncated>0</truncated>
		<difficult>0</difficult>
		<bndbox>
			<xmin>346</xmin>
			<ymin>720</ymin>
			<xmax>364</xmax>
			<ymax>811</ymax>
		</bndbox>
	</object>
	<object>
		<name>l1semibreve_7</name>
		<pose>Unspecified</pose>
		<truncated>0</truncated>
		<difficult>0</difficult>
		<bndbox>
			<xmin>361</xmin>
			<ymin>728</ymin>
			<xmax>377</xmax>
			<ymax>814</ymax>
		</bndbox>
	</object>
	<object>
		<name>o1semibreve_6</name>
		<pose>Unspecified</pose>
		<truncated>0</truncated>
		<difficult>0</difficult>
		<bndbox>
			<xmin>377</xmin>
			<ymin>768</ymin>
			<xmax>389</xmax>
			<ymax>820</ymax>
		</bndbox>
	</object>
	<object>
		<name>o2breve_8</name>
		<pose>Unspecified</pose>
		<truncated>0</truncated>
		<difficult>0</difficult>
		<bndbox>
			<xmin>388</xmin>
			<ymin>768</ymin>
			<xmax>405</xmax>
			<ymax>818</ymax>
		</bndbox>
	</object>
	<object>
		<name>breve_9</name>
		<pose>Unspecified</pose>
		<truncated>0</truncated>
		<difficult>0</difficult>
		<bndbox>
			<xmin>407</xmin>
			<ymin>810</ymin>
			<xmax>431</xmax>
			<ymax>843</ymax>
		</bndbox>
	</object>
	<object>
		<name>l1semibreve_8</name>
		<pose>Unspecified</pose>
		<truncated>0</truncated>
		<difficult>0</difficult>
		<bndbox>
			<xmin>439</xmin>
			<ymin>748</ymin>
			<xmax>460</xmax>
			<ymax>829</ymax>
		</bndbox>
	</object>
	<object>
		<name>l2semibreve_7</name>
		<pose>Unspecified</pose>
		<truncated>0</truncated>
		<difficult>0</difficult>
		<bndbox>
			<xmin>453</xmin>
			<ymin>793</ymin>
			<xmax>468</xmax>
			<ymax>824</ymax>
		</bndbox>
	</object>
	<object>
		<name>minim_6</name>
		<pose>Unspecified</pose>
		<truncated>0</truncated>
		<difficult>0</difficult>
		<bndbox>
			<xmin>466</xmin>
			<ymin>729</ymin>
			<xmax>484</xmax>
			<ymax>813</ymax>
		</bndbox>
	</object>
	<object>
		<name>minim_5</name>
		<pose>Unspecified</pose>
		<truncated>0</truncated>
		<difficult>0</difficult>
		<bndbox>
			<xmin>479</xmin>
			<ymin>716</ymin>
			<xmax>496</xmax>
			<ymax>796</ymax>
		</bndbox>
	</object>
	<object>
		<name>semibreve_4</name>
		<pose>Unspecified</pose>
		<truncated>0</truncated>
		<difficult>0</difficult>
		<bndbox>
			<xmin>493</xmin>
			<ymin>749</ymin>
			<xmax>510</xmax>
			<ymax>788</ymax>
		</bndbox>
	</object>
	<object>
		<name>point</name>
		<pose>Unspecified</pose>
		<truncated>0</truncated>
		<difficult>0</difficult>
		<bndbox>
			<xmin>503</xmin>
			<ymin>760</ymin>
			<xmax>518</xmax>
			<ymax>780</ymax>
		</bndbox>
	</object>
	<object>
		<name>semiminim_5</name>
		<pose>Unspecified</pose>
		<truncated>0</truncated>
		<difficult>0</difficult>
		<bndbox>
			<xmin>512</xmin>
			<ymin>707</ymin>
			<xmax>528</xmax>
			<ymax>805</ymax>
		</bndbox>
	</object>
	<object>
		<name>semiminim_6</name>
		<pose>Unspecified</pose>
		<truncated>0</truncated>
		<difficult>0</difficult>
		<bndbox>
			<xmin>525</xmin>
			<ymin>714</ymin>
			<xmax>543</xmax>
			<ymax>814</ymax>
		</bndbox>
	</object>
	<object>
		<name>semibreve_7</name>
		<pose>Unspecified</pose>
		<truncated>0</truncated>
		<difficult>0</difficult>
		<bndbox>
			<xmin>538</xmin>
			<ymin>781</ymin>
			<xmax>555</xmax>
			<ymax>822</ymax>
		</bndbox>
	</object>
	<object>
		<name>o1semibreve_8</name>
		<pose>Unspecified</pose>
		<truncated>0</truncated>
		<difficult>0</difficult>
		<bndbox>
			<xmin>553</xmin>
			<ymin>768</ymin>
			<xmax>573</xmax>
			<ymax>864</ymax>
		</bndbox>
	</object>
	<object>
		<name>o2semibreve_11</name>
		<pose>Unspecified</pose>
		<truncated>0</truncated>
		<difficult>0</difficult>
		<bndbox>
			<xmin>573</xmin>
			<ymin>768</ymin>
			<xmax>593</xmax>
			<ymax>864</ymax>
		</bndbox>
	</object>
	<object>
		<name>semibreve_8</name>
		<pose>Unspecified</pose>
		<truncated>0</truncated>
		<difficult>0</difficult>
		<bndbox>
			<xmin>590</xmin>
			<ymin>791</ymin>
			<xmax>608</xmax>
			<ymax>834</ymax>
		</bndbox>
	</object>
	<object>
		<name>semibreve rest</name>
		<pose>Unspecified</pose>
		<truncated>0</truncated>
		<difficult>0</difficult>
		<bndbox>
			<xmin>604</xmin>
			<ymin>745</ymin>
			<xmax>619</xmax>
			<ymax>856</ymax>
		</bndbox>
	</object>
	<object>
		<name>semibreve_5</name>
		<pose>Unspecified</pose>
		<truncated>0</truncated>
		<difficult>0</difficult>
		<bndbox>
			<xmin>614</xmin>
			<ymin>756</ymin>
			<xmax>631</xmax>
			<ymax>795</ymax>
		</bndbox>
	</object>
	<object>
		<name>point</name>
		<pose>Unspecified</pose>
		<truncated>0</truncated>
		<difficult>0</difficult>
		<bndbox>
			<xmin>622</xmin>
			<ymin>778</ymin>
			<xmax>634</xmax>
			<ymax>794</ymax>
		</bndbox>
	</object>
	<object>
		<name>minim_7</name>
		<pose>Unspecified</pose>
		<truncated>0</truncated>
		<difficult>0</difficult>
		<bndbox>
			<xmin>629</xmin>
			<ymin>734</ymin>
			<xmax>645</xmax>
			<ymax>822</ymax>
		</bndbox>
	</object>
	<object>
		<name>semibreve_6</name>
		<pose>Unspecified</pose>
		<truncated>0</truncated>
		<difficult>0</difficult>
		<bndbox>
			<xmin>643</xmin>
			<ymin>774</ymin>
			<xmax>657</xmax>
			<ymax>810</ymax>
		</bndbox>
	</object>
	<object>
		<name>breve_5</name>
		<pose>Unspecified</pose>
		<truncated>0</truncated>
		<difficult>0</difficult>
		<bndbox>
			<xmin>651</xmin>
			<ymin>760</ymin>
			<xmax>672</xmax>
			<ymax>792</ymax>
		</bndbox>
	</object>
	<object>
		<name>semibreve_6</name>
		<pose>Unspecified</pose>
		<truncated>0</truncated>
		<difficult>0</difficult>
		<bndbox>
			<xmin>670</xmin>
			<ymin>773</ymin>
			<xmax>686</xmax>
			<ymax>812</ymax>
		</bndbox>
	</object>
	<object>
		<name>minim_7</name>
		<pose>Unspecified</pose>
		<truncated>0</truncated>
		<difficult>0</difficult>
		<bndbox>
			<xmin>682</xmin>
			<ymin>735</ymin>
			<xmax>699</xmax>
			<ymax>828</ymax>
		</bndbox>
	</object>
	<object>
		<name>minim_6</name>
		<pose>Unspecified</pose>
		<truncated>0</truncated>
		<difficult>0</difficult>
		<bndbox>
			<xmin>698</xmin>
			<ymin>723</ymin>
			<xmax>715</xmax>
			<ymax>814</ymax>
		</bndbox>
	</object>
	<object>
		<name>minim_8</name>
		<pose>Unspecified</pose>
		<truncated>0</truncated>
		<difficult>0</difficult>
		<bndbox>
			<xmin>712</xmin>
			<ymin>735</ymin>
			<xmax>727</xmax>
			<ymax>840</ymax>
		</bndbox>
	</object>
	<object>
		<name>semibreve_7</name>
		<pose>Unspecified</pose>
		<truncated>0</truncated>
		<difficult>0</difficult>
		<bndbox>
			<xmin>723</xmin>
			<ymin>785</ymin>
			<xmax>741</xmax>
			<ymax>823</ymax>
		</bndbox>
	</object>
	<object>
		<name>minim_6</name>
		<pose>Unspecified</pose>
		<truncated>0</truncated>
		<difficult>0</difficult>
		<bndbox>
			<xmin>736</xmin>
			<ymin>727</ymin>
			<xmax>751</xmax>
			<ymax>814</ymax>
		</bndbox>
	</object>
	<object>
		<name>semibreve_5</name>
		<pose>Unspecified</pose>
		<truncated>0</truncated>
		<difficult>0</difficult>
		<bndbox>
			<xmin>748</xmin>
			<ymin>759</ymin>
			<xmax>765</xmax>
			<ymax>797</ymax>
		</bndbox>
	</object>
	<object>
		<name>custos_6</name>
		<pose>Unspecified</pose>
		<truncated>0</truncated>
		<difficult>0</difficult>
		<bndbox>
			<xmin>764</xmin>
			<ymin>750</ymin>
			<xmax>808</xmax>
			<ymax>815</ymax>
		</bndbox>
	</object>
	<object>
		<name>breve_11</name>
		<pose>Unspecified</pose>
		<truncated>0</truncated>
		<difficult>0</difficult>
		<bndbox>
			<xmin>425</xmin>
			<ymin>838</ymin>
			<xmax>449</xmax>
			<ymax>862</ymax>
		</bndbox>
	</object>
</annotation>
