<annotation>
	<folder>leuven-chansonnier_110_49v</folder>
	<filename>leuven-chansonnier_110_49v_1.jpeg</filename>
	<path>/home/yoeri/Work/OMR/data/Train/object_detection_data/non-public/annotated_source_images/revised_ground_truth/IDEM/Leuven_Chansonnier/leuven-chansonnier_110_49v/leuven-chansonnier_110_49v_1.jpeg</path>
	<source>
		<database>Unknown</database>
	</source>
	<size>
		<width>1024</width>
		<height>1566</height>
		<depth>3</depth>
	</size>
	<segmented>0</segmented>
	<object>
		<name>g clef_9</name>
		<pose>Unspecified</pose>
		<truncated>0</truncated>
		<difficult>0</difficult>
		<bndbox>
			<xmin>347</xmin>
			<ymin>668</ymin>
			<xmax>388</xmax>
			<ymax>755</ymax>
		</bndbox>
	</object>
	<object>
		<name>breve_4</name>
		<pose>Unspecified</pose>
		<truncated>0</truncated>
		<difficult>0</difficult>
		<bndbox>
			<xmin>407</xmin>
			<ymin>644</ymin>
			<xmax>435</xmax>
			<ymax>678</ymax>
		</bndbox>
	</object>
	<object>
		<name>semibreve_4</name>
		<pose>Unspecified</pose>
		<truncated>0</truncated>
		<difficult>0</difficult>
		<bndbox>
			<xmin>448</xmin>
			<ymin>637</ymin>
			<xmax>471</xmax>
			<ymax>681</ymax>
		</bndbox>
	</object>
	<object>
		<name>semibreve_4</name>
		<pose>Unspecified</pose>
		<truncated>0</truncated>
		<difficult>0</difficult>
		<bndbox>
			<xmin>477</xmin>
			<ymin>640</ymin>
			<xmax>501</xmax>
			<ymax>683</ymax>
		</bndbox>
	</object>
	<object>
		<name>breve_3</name>
		<pose>Unspecified</pose>
		<truncated>0</truncated>
		<difficult>0</difficult>
		<bndbox>
			<xmin>507</xmin>
			<ymin>635</ymin>
			<xmax>538</xmax>
			<ymax>669</ymax>
		</bndbox>
	</object>
	<object>
		<name>semibreve_3</name>
		<pose>Unspecified</pose>
		<truncated>0</truncated>
		<difficult>0</difficult>
		<bndbox>
			<xmin>546</xmin>
			<ymin>635</ymin>
			<xmax>569</xmax>
			<ymax>677</ymax>
		</bndbox>
	</object>
	<object>
		<name>semibreve_3</name>
		<pose>Unspecified</pose>
		<truncated>0</truncated>
		<difficult>0</difficult>
		<bndbox>
			<xmin>572</xmin>
			<ymin>635</ymin>
			<xmax>594</xmax>
			<ymax>678</ymax>
		</bndbox>
	</object>
	<object>
		<name>semibreve_4</name>
		<pose>Unspecified</pose>
		<truncated>0</truncated>
		<difficult>0</difficult>
		<bndbox>
			<xmin>604</xmin>
			<ymin>641</ymin>
			<xmax>629</xmax>
			<ymax>685</ymax>
		</bndbox>
	</object>
	<object>
		<name>semibreve_5</name>
		<pose>Unspecified</pose>
		<truncated>0</truncated>
		<difficult>0</difficult>
		<bndbox>
			<xmin>636</xmin>
			<ymin>648</ymin>
			<xmax>657</xmax>
			<ymax>692</ymax>
		</bndbox>
	</object>
	<object>
		<name>point</name>
		<pose>Unspecified</pose>
		<truncated>0</truncated>
		<difficult>0</difficult>
		<bndbox>
			<xmin>650</xmin>
			<ymin>656</ymin>
			<xmax>668</xmax>
			<ymax>680</ymax>
		</bndbox>
	</object>
	<object>
		<name>minim_6</name>
		<pose>Unspecified</pose>
		<truncated>0</truncated>
		<difficult>0</difficult>
		<bndbox>
			<xmin>669</xmin>
			<ymin>633</ymin>
			<xmax>691</xmax>
			<ymax>699</ymax>
		</bndbox>
	</object>
	<object>
		<name>breve_6</name>
		<pose>Unspecified</pose>
		<truncated>0</truncated>
		<difficult>0</difficult>
		<bndbox>
			<xmin>693</xmin>
			<ymin>661</ymin>
			<xmax>724</xmax>
			<ymax>693</ymax>
		</bndbox>
	</object>
	<object>
		<name>semibreve_7</name>
		<pose>Unspecified</pose>
		<truncated>0</truncated>
		<difficult>0</difficult>
		<bndbox>
			<xmin>722</xmin>
			<ymin>665</ymin>
			<xmax>746</xmax>
			<ymax>708</ymax>
		</bndbox>
	</object>
	<object>
		<name>breve_6</name>
		<pose>Unspecified</pose>
		<truncated>0</truncated>
		<difficult>0</difficult>
		<bndbox>
			<xmin>747</xmin>
			<ymin>661</ymin>
			<xmax>772</xmax>
			<ymax>701</ymax>
		</bndbox>
	</object>
	<object>
		<name>o1semibreve_8</name>
		<pose>Unspecified</pose>
		<truncated>0</truncated>
		<difficult>0</difficult>
		<bndbox>
			<xmin>775</xmin>
			<ymin>636</ymin>
			<xmax>794</xmax>
			<ymax>721</ymax>
		</bndbox>
	</object>
	<object>
		<name>o2semibreve_10</name>
		<pose>Unspecified</pose>
		<truncated>0</truncated>
		<difficult>0</difficult>
		<bndbox>
			<xmin>794</xmin>
			<ymin>636</ymin>
			<xmax>813</xmax>
			<ymax>725</ymax>
		</bndbox>
	</object>
	<object>
		<name>custos_9</name>
		<pose>Unspecified</pose>
		<truncated>0</truncated>
		<difficult>0</difficult>
		<bndbox>
			<xmin>810</xmin>
			<ymin>678</ymin>
			<xmax>853</xmax>
			<ymax>715</ymax>
		</bndbox>
	</object>
</annotation>
