<annotation>
	<folder>Capp.Sist.15_0095_fa_0046r_m</folder>
	<filename>Capp.Sist.15_0095_fa_0046r_m_5.jpg</filename>
	<path>/home/yoeri/Work/OMR/data/Train/object_detection_data/non-public/annotated_source_images/revised_ground_truth/IDEM/Capp.Sist.15/Capp.Sist.15_0095_fa_0046r_m/Capp.Sist.15_0095_fa_0046r_m_5.jpg</path>
	<source>
		<database>Unknown</database>
	</source>
	<size>
		<width>1940</width>
		<height>2718</height>
		<depth>3</depth>
	</size>
	<segmented>0</segmented>
	<object>
		<name>Imincut</name>
		<pose>Unspecified</pose>
		<truncated>0</truncated>
		<difficult>0</difficult>
		<bndbox>
			<xmin>650</xmin>
			<ymin>1447</ymin>
			<xmax>688</xmax>
			<ymax>1534</ymax>
		</bndbox>
	</object>
	<object>
		<name>breve_10</name>
		<pose>Unspecified</pose>
		<truncated>0</truncated>
		<difficult>0</difficult>
		<bndbox>
			<xmin>738</xmin>
			<ymin>1505</ymin>
			<xmax>790</xmax>
			<ymax>1546</ymax>
		</bndbox>
	</object>
	<object>
		<name>semibreve_7</name>
		<pose>Unspecified</pose>
		<truncated>0</truncated>
		<difficult>0</difficult>
		<bndbox>
			<xmin>879</xmin>
			<ymin>1472</ymin>
			<xmax>916</xmax>
			<ymax>1523</ymax>
		</bndbox>
	</object>
	<object>
		<name>l2semibreve_5</name>
		<pose>Unspecified</pose>
		<truncated>0</truncated>
		<difficult>0</difficult>
		<bndbox>
			<xmin>959</xmin>
			<ymin>1422</ymin>
			<xmax>993</xmax>
			<ymax>1499</ymax>
		</bndbox>
	</object>
	<object>
		<name>l2breve_4</name>
		<pose>Unspecified</pose>
		<truncated>0</truncated>
		<difficult>0</difficult>
		<bndbox>
			<xmin>994</xmin>
			<ymin>1425</ymin>
			<xmax>1021</xmax>
			<ymax>1475</ymax>
		</bndbox>
	</object>
	<object>
		<name>colored breve_3</name>
		<pose>Unspecified</pose>
		<truncated>0</truncated>
		<difficult>0</difficult>
		<bndbox>
			<xmin>1030</xmin>
			<ymin>1418</ymin>
			<xmax>1085</xmax>
			<ymax>1473</ymax>
		</bndbox>
	</object>
	<object>
		<name>colored semibreve_4</name>
		<pose>Unspecified</pose>
		<truncated>0</truncated>
		<difficult>0</difficult>
		<bndbox>
			<xmin>1069</xmin>
			<ymin>1415</ymin>
			<xmax>1147</xmax>
			<ymax>1493</ymax>
		</bndbox>
	</object>
	<object>
		<name>o1semibreve_5</name>
		<pose>Unspecified</pose>
		<truncated>0</truncated>
		<difficult>0</difficult>
		<bndbox>
			<xmin>1136</xmin>
			<ymin>1378</ymin>
			<xmax>1168</xmax>
			<ymax>1512</ymax>
		</bndbox>
	</object>
	<object>
		<name>o2semibreve_6</name>
		<pose>Unspecified</pose>
		<truncated>0</truncated>
		<difficult>0</difficult>
		<bndbox>
			<xmin>1168</xmin>
			<ymin>1378</ymin>
			<xmax>1203</xmax>
			<ymax>1512</ymax>
		</bndbox>
	</object>
	<object>
		<name>l2breve_6</name>
		<pose>Unspecified</pose>
		<truncated>0</truncated>
		<difficult>0</difficult>
		<bndbox>
			<xmin>1261</xmin>
			<ymin>1451</ymin>
			<xmax>1288</xmax>
			<ymax>1499</ymax>
		</bndbox>
	</object>
	<object>
		<name>semibreve_6</name>
		<pose>Unspecified</pose>
		<truncated>0</truncated>
		<difficult>0</difficult>
		<bndbox>
			<xmin>1304</xmin>
			<ymin>1432</ymin>
			<xmax>1355</xmax>
			<ymax>1515</ymax>
		</bndbox>
	</object>
	<object>
		<name>semibreve_6</name>
		<pose>Unspecified</pose>
		<truncated>0</truncated>
		<difficult>0</difficult>
		<bndbox>
			<xmin>1358</xmin>
			<ymin>1455</ymin>
			<xmax>1401</xmax>
			<ymax>1507</ymax>
		</bndbox>
	</object>
	<object>
		<name>l1longa_10</name>
		<pose>Unspecified</pose>
		<truncated>0</truncated>
		<difficult>0</difficult>
		<bndbox>
			<xmin>1420</xmin>
			<ymin>1502</ymin>
			<xmax>1456</xmax>
			<ymax>1599</ymax>
		</bndbox>
	</object>
	<object>
		<name>l2breve_9</name>
		<pose>Unspecified</pose>
		<truncated>0</truncated>
		<difficult>0</difficult>
		<bndbox>
			<xmin>1439</xmin>
			<ymin>1487</ymin>
			<xmax>1490</xmax>
			<ymax>1530</ymax>
		</bndbox>
	</object>
	<object>
		<name>breve_7</name>
		<pose>Unspecified</pose>
		<truncated>0</truncated>
		<difficult>0</difficult>
		<bndbox>
			<xmin>1489</xmin>
			<ymin>1456</ymin>
			<xmax>1553</xmax>
			<ymax>1521</ymax>
		</bndbox>
	</object>
	<object>
		<name>f clef_5</name>
		<pose>Unspecified</pose>
		<truncated>0</truncated>
		<difficult>0</difficult>
		<bndbox>
			<xmin>564</xmin>
			<ymin>1407</ymin>
			<xmax>637</xmax>
			<ymax>1523</ymax>
		</bndbox>
	</object>
	<object>
		<name>longa rest</name>
		<pose>Unspecified</pose>
		<truncated>0</truncated>
		<difficult>0</difficult>
		<bndbox>
			<xmin>700</xmin>
			<ymin>1430</ymin>
			<xmax>714</xmax>
			<ymax>1542</ymax>
		</bndbox>
	</object>
	<object>
		<name>longa rest</name>
		<pose>Unspecified</pose>
		<truncated>0</truncated>
		<difficult>0</difficult>
		<bndbox>
			<xmin>712</xmin>
			<ymin>1430</ymin>
			<xmax>726</xmax>
			<ymax>1542</ymax>
		</bndbox>
	</object>
	<object>
		<name>l1breve_7</name>
		<pose>Unspecified</pose>
		<truncated>0</truncated>
		<difficult>0</difficult>
		<bndbox>
			<xmin>1227</xmin>
			<ymin>1476</ymin>
			<xmax>1264</xmax>
			<ymax>1511</ymax>
		</bndbox>
	</object>
	<object>
		<name>breve_9</name>
		<pose>Unspecified</pose>
		<truncated>0</truncated>
		<difficult>0</difficult>
		<bndbox>
			<xmin>1585</xmin>
			<ymin>1517</ymin>
			<xmax>1624</xmax>
			<ymax>1558</ymax>
		</bndbox>
	</object>
	<object>
		<name>longa_8</name>
		<pose>Unspecified</pose>
		<truncated>0</truncated>
		<difficult>0</difficult>
		<bndbox>
			<xmin>1613</xmin>
			<ymin>1486</ymin>
			<xmax>1658</xmax>
			<ymax>1587</ymax>
		</bndbox>
	</object>
	<object>
		<name>l1longa_6</name>
		<pose>Unspecified</pose>
		<truncated>0</truncated>
		<difficult>0</difficult>
		<bndbox>
			<xmin>803</xmin>
			<ymin>1459</ymin>
			<xmax>844</xmax>
			<ymax>1545</ymax>
		</bndbox>
	</object>
	<object>
		<name>l2semibreve_5</name>
		<pose>Unspecified</pose>
		<truncated>0</truncated>
		<difficult>0</difficult>
		<bndbox>
			<xmin>843</xmin>
			<ymin>1446</ymin>
			<xmax>875</xmax>
			<ymax>1486</ymax>
		</bndbox>
	</object>
	<object>
		<name>l1semibreve_6</name>
		<pose>Unspecified</pose>
		<truncated>0</truncated>
		<difficult>0</difficult>
		<bndbox>
			<xmin>931</xmin>
			<ymin>1396</ymin>
			<xmax>969</xmax>
			<ymax>1494</ymax>
		</bndbox>
	</object>
</annotation>
