<annotation>
	<folder>Capp.Sist.15_0095_fa_0046r_m</folder>
	<filename>Capp.Sist.15_0095_fa_0046r_m_4.jpg</filename>
	<path>/home/yoeri/Work/OMR/data/Train/object_detection_data/non-public/annotated_source_images/revised_ground_truth/IDEM/Capp.Sist.15/Capp.Sist.15_0095_fa_0046r_m/Capp.Sist.15_0095_fa_0046r_m_4.jpg</path>
	<source>
		<database>Unknown</database>
	</source>
	<size>
		<width>1940</width>
		<height>2718</height>
		<depth>3</depth>
	</size>
	<segmented>0</segmented>
	<object>
		<name>c clef_7</name>
		<pose>Unspecified</pose>
		<truncated>0</truncated>
		<difficult>0</difficult>
		<bndbox>
			<xmin>439</xmin>
			<ymin>1068</ymin>
			<xmax>486</xmax>
			<ymax>1201</ymax>
		</bndbox>
	</object>
	<object>
		<name>minim_6</name>
		<pose>Unspecified</pose>
		<truncated>0</truncated>
		<difficult>0</difficult>
		<bndbox>
			<xmin>483</xmin>
			<ymin>1040</ymin>
			<xmax>526</xmax>
			<ymax>1165</ymax>
		</bndbox>
	</object>
	<object>
		<name>colored semibreve_4</name>
		<pose>Unspecified</pose>
		<truncated>0</truncated>
		<difficult>0</difficult>
		<bndbox>
			<xmin>528</xmin>
			<ymin>1055</ymin>
			<xmax>575</xmax>
			<ymax>1136</ymax>
		</bndbox>
	</object>
	<object>
		<name>semiminim_5</name>
		<pose>Unspecified</pose>
		<truncated>0</truncated>
		<difficult>0</difficult>
		<bndbox>
			<xmin>591</xmin>
			<ymin>1036</ymin>
			<xmax>628</xmax>
			<ymax>1146</ymax>
		</bndbox>
	</object>
	<object>
		<name>semibreve_6</name>
		<pose>Unspecified</pose>
		<truncated>0</truncated>
		<difficult>0</difficult>
		<bndbox>
			<xmin>628</xmin>
			<ymin>1085</ymin>
			<xmax>674</xmax>
			<ymax>1163</ymax>
		</bndbox>
	</object>
	<object>
		<name>minim_9</name>
		<pose>Unspecified</pose>
		<truncated>0</truncated>
		<difficult>0</difficult>
		<bndbox>
			<xmin>670</xmin>
			<ymin>1068</ymin>
			<xmax>712</xmax>
			<ymax>1191</ymax>
		</bndbox>
	</object>
	<object>
		<name>semibreve_6</name>
		<pose>Unspecified</pose>
		<truncated>0</truncated>
		<difficult>0</difficult>
		<bndbox>
			<xmin>716</xmin>
			<ymin>1074</ymin>
			<xmax>759</xmax>
			<ymax>1159</ymax>
		</bndbox>
	</object>
	<object>
		<name>semibreve_6</name>
		<pose>Unspecified</pose>
		<truncated>0</truncated>
		<difficult>0</difficult>
		<bndbox>
			<xmin>759</xmin>
			<ymin>1076</ymin>
			<xmax>808</xmax>
			<ymax>1161</ymax>
		</bndbox>
	</object>
	<object>
		<name>colored semibreve_7</name>
		<pose>Unspecified</pose>
		<truncated>0</truncated>
		<difficult>0</difficult>
		<bndbox>
			<xmin>810</xmin>
			<ymin>1091</ymin>
			<xmax>862</xmax>
			<ymax>1170</ymax>
		</bndbox>
	</object>
	<object>
		<name>semiminim_8</name>
		<pose>Unspecified</pose>
		<truncated>0</truncated>
		<difficult>0</difficult>
		<bndbox>
			<xmin>865</xmin>
			<ymin>1064</ymin>
			<xmax>903</xmax>
			<ymax>1180</ymax>
		</bndbox>
	</object>
	<object>
		<name>minim_10</name>
		<pose>Unspecified</pose>
		<truncated>0</truncated>
		<difficult>0</difficult>
		<bndbox>
			<xmin>907</xmin>
			<ymin>1079</ymin>
			<xmax>951</xmax>
			<ymax>1212</ymax>
		</bndbox>
	</object>
	<object>
		<name>semibreve_9</name>
		<pose>Unspecified</pose>
		<truncated>0</truncated>
		<difficult>0</difficult>
		<bndbox>
			<xmin>956</xmin>
			<ymin>1112</ymin>
			<xmax>1004</xmax>
			<ymax>1197</ymax>
		</bndbox>
	</object>
	<object>
		<name>minim_10</name>
		<pose>Unspecified</pose>
		<truncated>0</truncated>
		<difficult>0</difficult>
		<bndbox>
			<xmin>1004</xmin>
			<ymin>1079</ymin>
			<xmax>1047</xmax>
			<ymax>1204</ymax>
		</bndbox>
	</object>
	<object>
		<name>longa_9</name>
		<pose>Unspecified</pose>
		<truncated>0</truncated>
		<difficult>0</difficult>
		<bndbox>
			<xmin>1050</xmin>
			<ymin>1112</ymin>
			<xmax>1115</xmax>
			<ymax>1227</ymax>
		</bndbox>
	</object>
	<object>
		<name>barline</name>
		<pose>Unspecified</pose>
		<truncated>0</truncated>
		<difficult>0</difficult>
		<bndbox>
			<xmin>1110</xmin>
			<ymin>1066</ymin>
			<xmax>1146</xmax>
			<ymax>1204</ymax>
		</bndbox>
	</object>
</annotation>
