<annotation>
	<folder>30_031_15r_6988_8533</folder>
	<filename>30_031_15r_6988_8533_3.jpeg</filename>
	<path>/home/yoeri/Work/OMR/data/Train/object_detection_data/non-public/annotated_source_images/revised_ground_truth/IDEM/B-Br_MSIV.922/30_031_15r_6988_8533/30_031_15r_6988_8533_3.jpeg</path>
	<source>
		<database>Unknown</database>
	</source>
	<size>
		<width>1024</width>
		<height>1250</height>
		<depth>3</depth>
	</size>
	<segmented>0</segmented>
	<object>
		<name>c clef_7</name>
		<pose>Unspecified</pose>
		<truncated>0</truncated>
		<difficult>0</difficult>
		<bndbox>
			<xmin>168</xmin>
			<ymin>394</ymin>
			<xmax>191</xmax>
			<ymax>455</ymax>
		</bndbox>
	</object>
	<object>
		<name>minim_6</name>
		<pose>Unspecified</pose>
		<truncated>0</truncated>
		<difficult>0</difficult>
		<bndbox>
			<xmin>202</xmin>
			<ymin>384</ymin>
			<xmax>221</xmax>
			<ymax>435</ymax>
		</bndbox>
	</object>
	<object>
		<name>minim_13</name>
		<pose>Unspecified</pose>
		<truncated>0</truncated>
		<difficult>0</difficult>
		<bndbox>
			<xmin>223</xmin>
			<ymin>426</ymin>
			<xmax>239</xmax>
			<ymax>477</ymax>
		</bndbox>
	</object>
	<object>
		<name>point</name>
		<pose>Unspecified</pose>
		<truncated>0</truncated>
		<difficult>0</difficult>
		<bndbox>
			<xmin>232</xmin>
			<ymin>446</ymin>
			<xmax>245</xmax>
			<ymax>463</ymax>
		</bndbox>
	</object>
	<object>
		<name>semiminim_12</name>
		<pose>Unspecified</pose>
		<truncated>0</truncated>
		<difficult>0</difficult>
		<bndbox>
			<xmin>244</xmin>
			<ymin>416</ymin>
			<xmax>261</xmax>
			<ymax>470</ymax>
		</bndbox>
	</object>
	<object>
		<name>semiminim_11</name>
		<pose>Unspecified</pose>
		<truncated>0</truncated>
		<difficult>0</difficult>
		<bndbox>
			<xmin>261</xmin>
			<ymin>411</ymin>
			<xmax>278</xmax>
			<ymax>465</ymax>
		</bndbox>
	</object>
	<object>
		<name>semiminim_10</name>
		<pose>Unspecified</pose>
		<truncated>0</truncated>
		<difficult>0</difficult>
		<bndbox>
			<xmin>282</xmin>
			<ymin>403</ymin>
			<xmax>299</xmax>
			<ymax>459</ymax>
		</bndbox>
	</object>
	<object>
		<name>minim_9</name>
		<pose>Unspecified</pose>
		<truncated>0</truncated>
		<difficult>0</difficult>
		<bndbox>
			<xmin>299</xmin>
			<ymin>397</ymin>
			<xmax>318</xmax>
			<ymax>455</ymax>
		</bndbox>
	</object>
	<object>
		<name>minim_6</name>
		<pose>Unspecified</pose>
		<truncated>0</truncated>
		<difficult>0</difficult>
		<bndbox>
			<xmin>330</xmin>
			<ymin>384</ymin>
			<xmax>349</xmax>
			<ymax>438</ymax>
		</bndbox>
	</object>
	<object>
		<name>point</name>
		<pose>Unspecified</pose>
		<truncated>0</truncated>
		<difficult>0</difficult>
		<bndbox>
			<xmin>343</xmin>
			<ymin>412</ymin>
			<xmax>357</xmax>
			<ymax>431</ymax>
		</bndbox>
	</object>
	<object>
		<name>semiminim_7</name>
		<pose>Unspecified</pose>
		<truncated>0</truncated>
		<difficult>0</difficult>
		<bndbox>
			<xmin>354</xmin>
			<ymin>391</ymin>
			<xmax>370</xmax>
			<ymax>446</ymax>
		</bndbox>
	</object>
	<object>
		<name>semiminim_8</name>
		<pose>Unspecified</pose>
		<truncated>0</truncated>
		<difficult>0</difficult>
		<bndbox>
			<xmin>372</xmin>
			<ymin>395</ymin>
			<xmax>387</xmax>
			<ymax>451</ymax>
		</bndbox>
	</object>
	<object>
		<name>semiminim_9</name>
		<pose>Unspecified</pose>
		<truncated>0</truncated>
		<difficult>0</difficult>
		<bndbox>
			<xmin>387</xmin>
			<ymin>401</ymin>
			<xmax>404</xmax>
			<ymax>456</ymax>
		</bndbox>
	</object>
	<object>
		<name>longa_8</name>
		<pose>Unspecified</pose>
		<truncated>0</truncated>
		<difficult>0</difficult>
		<bndbox>
			<xmin>410</xmin>
			<ymin>418</ymin>
			<xmax>441</xmax>
			<ymax>481</ymax>
		</bndbox>
	</object>
	<object>
		<name>barline</name>
		<pose>Unspecified</pose>
		<truncated>0</truncated>
		<difficult>0</difficult>
		<bndbox>
			<xmin>438</xmin>
			<ymin>399</ymin>
			<xmax>458</xmax>
			<ymax>465</ymax>
		</bndbox>
	</object>
</annotation>
