<annotation>
	<folder>A-Wn_15495_004_4697_6798</folder>
	<filename>A-Wn_15495_004_4697_6798_0.jpeg</filename>
	<path>/home/yoeri/Work/OMR/data/Train/object_detection_data/non-public/annotated_source_images/revised_ground_truth/IDEM/A-Wn_15495/A-Wn_15495_004_4697_6798/A-Wn_15495_004_4697_6798_0.jpeg</path>
	<source>
		<database>Unknown</database>
	</source>
	<size>
		<width>1024</width>
		<height>1482</height>
		<depth>3</depth>
	</size>
	<segmented>0</segmented>
	<object>
		<name>c clef_7</name>
		<pose>Unspecified</pose>
		<truncated>0</truncated>
		<difficult>0</difficult>
		<bndbox>
			<xmin>365</xmin>
			<ymin>112</ymin>
			<xmax>394</xmax>
			<ymax>191</ymax>
		</bndbox>
	</object>
	<object>
		<name>Pmincut</name>
		<pose>Unspecified</pose>
		<truncated>0</truncated>
		<difficult>0</difficult>
		<bndbox>
			<xmin>393</xmin>
			<ymin>82</ymin>
			<xmax>436</xmax>
			<ymax>167</ymax>
		</bndbox>
	</object>
	<object>
		<name>breve_5</name>
		<pose>Unspecified</pose>
		<truncated>0</truncated>
		<difficult>0</difficult>
		<bndbox>
			<xmin>443</xmin>
			<ymin>114</ymin>
			<xmax>479</xmax>
			<ymax>158</ymax>
		</bndbox>
	</object>
	<object>
		<name>minim_4</name>
		<pose>Unspecified</pose>
		<truncated>0</truncated>
		<difficult>0</difficult>
		<bndbox>
			<xmin>477</xmin>
			<ymin>73</ymin>
			<xmax>499</xmax>
			<ymax>148</ymax>
		</bndbox>
	</object>
	<object>
		<name>point</name>
		<pose>Unspecified</pose>
		<truncated>0</truncated>
		<difficult>0</difficult>
		<bndbox>
			<xmin>492</xmin>
			<ymin>114</ymin>
			<xmax>510</xmax>
			<ymax>138</ymax>
		</bndbox>
	</object>
	<object>
		<name>semiminim_5</name>
		<pose>Unspecified</pose>
		<truncated>0</truncated>
		<difficult>0</difficult>
		<bndbox>
			<xmin>509</xmin>
			<ymin>78</ymin>
			<xmax>529</xmax>
			<ymax>156</ymax>
		</bndbox>
	</object>
	<object>
		<name>minim_7</name>
		<pose>Unspecified</pose>
		<truncated>0</truncated>
		<difficult>0</difficult>
		<bndbox>
			<xmin>525</xmin>
			<ymin>91</ymin>
			<xmax>545</xmax>
			<ymax>170</ymax>
		</bndbox>
	</object>
	<object>
		<name>semibreve_3</name>
		<pose>Unspecified</pose>
		<truncated>0</truncated>
		<difficult>0</difficult>
		<bndbox>
			<xmin>543</xmin>
			<ymin>100</ymin>
			<xmax>562</xmax>
			<ymax>138</ymax>
		</bndbox>
	</object>
	<object>
		<name>minim_4</name>
		<pose>Unspecified</pose>
		<truncated>0</truncated>
		<difficult>0</difficult>
		<bndbox>
			<xmin>560</xmin>
			<ymin>80</ymin>
			<xmax>581</xmax>
			<ymax>145</ymax>
		</bndbox>
	</object>
	<object>
		<name>semibreve_3</name>
		<pose>Unspecified</pose>
		<truncated>0</truncated>
		<difficult>0</difficult>
		<bndbox>
			<xmin>580</xmin>
			<ymin>97</ymin>
			<xmax>603</xmax>
			<ymax>142</ymax>
		</bndbox>
	</object>
	<object>
		<name>point</name>
		<pose>Unspecified</pose>
		<truncated>0</truncated>
		<difficult>0</difficult>
		<bndbox>
			<xmin>594</xmin>
			<ymin>98</ymin>
			<xmax>617</xmax>
			<ymax>133</ymax>
		</bndbox>
	</object>
	<object>
		<name>minim_4</name>
		<pose>Unspecified</pose>
		<truncated>0</truncated>
		<difficult>0</difficult>
		<bndbox>
			<xmin>609</xmin>
			<ymin>72</ymin>
			<xmax>630</xmax>
			<ymax>148</ymax>
		</bndbox>
	</object>
	<object>
		<name>minim_3</name>
		<pose>Unspecified</pose>
		<truncated>0</truncated>
		<difficult>0</difficult>
		<bndbox>
			<xmin>630</xmin>
			<ymin>71</ymin>
			<xmax>651</xmax>
			<ymax>139</ymax>
		</bndbox>
	</object>
	<object>
		<name>minim_7</name>
		<pose>Unspecified</pose>
		<truncated>0</truncated>
		<difficult>0</difficult>
		<bndbox>
			<xmin>649</xmin>
			<ymin>91</ymin>
			<xmax>669</xmax>
			<ymax>171</ymax>
		</bndbox>
	</object>
	<object>
		<name>minim rest</name>
		<pose>Unspecified</pose>
		<truncated>0</truncated>
		<difficult>0</difficult>
		<bndbox>
			<xmin>671</xmin>
			<ymin>103</ymin>
			<xmax>686</xmax>
			<ymax>192</ymax>
		</bndbox>
	</object>
	<object>
		<name>minim_7</name>
		<pose>Unspecified</pose>
		<truncated>0</truncated>
		<difficult>0</difficult>
		<bndbox>
			<xmin>686</xmin>
			<ymin>93</ymin>
			<xmax>708</xmax>
			<ymax>169</ymax>
		</bndbox>
	</object>
	<object>
		<name>semibreve_6</name>
		<pose>Unspecified</pose>
		<truncated>0</truncated>
		<difficult>0</difficult>
		<bndbox>
			<xmin>708</xmin>
			<ymin>121</ymin>
			<xmax>729</xmax>
			<ymax>160</ymax>
		</bndbox>
	</object>
	<object>
		<name>minim_8</name>
		<pose>Unspecified</pose>
		<truncated>0</truncated>
		<difficult>0</difficult>
		<bndbox>
			<xmin>726</xmin>
			<ymin>103</ymin>
			<xmax>745</xmax>
			<ymax>180</ymax>
		</bndbox>
	</object>
	<object>
		<name>minim_7</name>
		<pose>Unspecified</pose>
		<truncated>0</truncated>
		<difficult>0</difficult>
		<bndbox>
			<xmin>743</xmin>
			<ymin>94</ymin>
			<xmax>764</xmax>
			<ymax>166</ymax>
		</bndbox>
	</object>
	<object>
		<name>minim_9</name>
		<pose>Unspecified</pose>
		<truncated>0</truncated>
		<difficult>0</difficult>
		<bndbox>
			<xmin>762</xmin>
			<ymin>106</ymin>
			<xmax>783</xmax>
			<ymax>187</ymax>
		</bndbox>
	</object>
	<object>
		<name>minim_10</name>
		<pose>Unspecified</pose>
		<truncated>0</truncated>
		<difficult>0</difficult>
		<bndbox>
			<xmin>781</xmin>
			<ymin>116</ymin>
			<xmax>800</xmax>
			<ymax>190</ymax>
		</bndbox>
	</object>
	<object>
		<name>l1semibreve_9</name>
		<pose>Unspecified</pose>
		<truncated>0</truncated>
		<difficult>0</difficult>
		<bndbox>
			<xmin>800</xmin>
			<ymin>109</ymin>
			<xmax>824</xmax>
			<ymax>184</ymax>
		</bndbox>
	</object>
	<object>
		<name>l2colored semibreve_8</name>
		<pose>Unspecified</pose>
		<truncated>0</truncated>
		<difficult>0</difficult>
		<bndbox>
			<xmin>817</xmin>
			<ymin>144</ymin>
			<xmax>840</xmax>
			<ymax>180</ymax>
		</bndbox>
	</object>
	<object>
		<name>semiminim_7</name>
		<pose>Unspecified</pose>
		<truncated>0</truncated>
		<difficult>0</difficult>
		<bndbox>
			<xmin>840</xmin>
			<ymin>92</ymin>
			<xmax>862</xmax>
			<ymax>176</ymax>
		</bndbox>
	</object>
	<object>
		<name>custos_6</name>
		<pose>Unspecified</pose>
		<truncated>0</truncated>
		<difficult>0</difficult>
		<bndbox>
			<xmin>865</xmin>
			<ymin>117</ymin>
			<xmax>892</xmax>
			<ymax>158</ymax>
		</bndbox>
	</object>
</annotation>
